tsanley/__init__.py
tsanley/annotate/__init__.py
tsanley/annotate/annotate.py
tsanley/dynamic/__init__.py
tsanley/dynamic/dynamic_shape_analyzer.py
tsanley/dynamic/eval_utils.py
tsanley/dynamic/shape_cache.py
tsanley/dynamic/trace_utils.py
tsanley-0.2.0.data/scripts/tsa
tsanley-0.2.0.dist-info/LICENSE
tsanley-0.2.0.dist-info/METADATA
tsanley-0.2.0.dist-info/WHEEL
tsanley-0.2.0.dist-info/top_level.txt
tsanley-0.2.0.dist-info/RECORD
