Metadata-Version: 2.1
Name: tsanley
Version: 0.2.0
Summary: Tsanley: Understanding Tensor Programs
Home-page: https://github.com/ofnote/tsanley
Author: Nishant Sinha
Author-email: nishant@offnote.co
License: Apache 2.0
Platform: POSIX
Classifier: Environment :: Console
Classifier: Intended Audience :: Developers
Classifier: License :: OSI Approved :: Apache Software License
Classifier: Operating System :: OS Independent
Classifier: Programming Language :: Python :: 3.6
Classifier: Programming Language :: Python :: 3.7
Classifier: Topic :: Software Development
Classifier: Topic :: Scientific/Engineering :: Artificial Intelligence
Requires-Dist: sympy
Requires-Dist: typed-ast
Requires-Dist: typed-astunparse
Requires-Dist: easydict
Requires-Dist: astpretty
Requires-Dist: tsalib
